numeral/__init__.py
numeral/_version.py
numeral/numeral.py
numeral-0.1.0.17.dist-info/LICENSE.rst
numeral-0.1.0.17.dist-info/METADATA
numeral-0.1.0.17.dist-info/WHEEL
numeral-0.1.0.17.dist-info/top_level.txt
numeral-0.1.0.17.dist-info/RECORD
