Metadata-Version: 2.1
Name: numeral
Version: 0.1.0.17
Summary: Support for various integer-to-numeral conversion.
Home-page: https://github.com/norok2/numeral
Author: Riccardo Metere
Author-email: rick@metere.it
License: GPLv3+
Keywords: numeral,letter,alphabet,numeric,arabic,roman
Platform: UNKNOWN
Classifier: Development Status :: 4 - Beta
Classifier: Intended Audience :: Developers
Classifier: Intended Audience :: Science/Research
Classifier: Intended Audience :: Education
Classifier: Natural Language :: English
Classifier: Natural Language :: Latin
Classifier: Topic :: Software Development
Classifier: Topic :: Software Development :: Libraries
Classifier: Topic :: Software Development :: Localization
Classifier: Topic :: Text Processing
Classifier: Topic :: Text Processing :: Linguistic
Classifier: Topic :: Scientific/Engineering
Classifier: Topic :: Sociology :: History
Classifier: Topic :: Education
Classifier: Topic :: Utilities
Classifier: Operating System :: POSIX
Classifier: License :: OSI Approved :: GNU General Public License v3 or later (GPLv3+)
Classifier: Programming Language :: Python
Classifier: Programming Language :: Python :: 2
Classifier: Programming Language :: Python :: 3
